crytto/__init__.py
crytto/filecrypt.py
crytto/main.py
crytto/utils.py
crytto-0.7.5.dist-info/METADATA
crytto-0.7.5.dist-info/WHEEL
crytto-0.7.5.dist-info/entry_points.txt
crytto-0.7.5.dist-info/top_level.txt
crytto-0.7.5.dist-info/RECORD
